setup.py
gistributions/Binomialdistribution.py
gistributions/Gaussiandistribution.py
gistributions/Generaldistribution.py
gistributions/__init__.py
gistributions.egg-info/PKG-INFO
gistributions.egg-info/SOURCES.txt
gistributions.egg-info/dependency_links.txt
gistributions.egg-info/not-zip-safe
gistributions.egg-info/top_level.txt