Metadata-Version: 1.0
Name: gistributions
Version: 0.1
Summary: Gaussian distributions
Home-page: UNKNOWN
Author: Godwin
Author-email: justg.techs@gmail.com
License: UNKNOWN
Platform: UNKNOWN
